Database/__init__.py
Database/db_handler.py
cp015database-1.0.1.dist-info/METADATA
cp015database-1.0.1.dist-info/WHEEL
cp015database-1.0.1.dist-info/top_level.txt
cp015database-1.0.1.dist-info/RECORD
